feagi_agent/PIL_retina.py
feagi_agent/__init__.py
feagi_agent/actuators.py
feagi_agent/configuration.py
feagi_agent/feagi_interface.py
feagi_agent/pns_gateway.py
feagi_agent/retina.py
feagi_agent/router.py
feagi_agent/sensors.py
feagi_agent/testing_mode.py
feagi_agent/trainer.py
feagi_agent/version.py
feagi_agent/sensorimotor/__init__.py
feagi_agent-1.0.5.dist-info/LICENSE
feagi_agent-1.0.5.dist-info/METADATA
feagi_agent-1.0.5.dist-info/WHEEL
feagi_agent-1.0.5.dist-info/top_level.txt
feagi_agent-1.0.5.dist-info/RECORD
