Metadata-Version: 2.1
Name: feagi_agent
Version: 1.0.5
Summary: Feagi agent to work with general and simulation robots
Home-page: https://github.com/feagi/feagi
Author: Neuraville Inc.
Author-email: info@feagi.org
Project-URL: Bug Tracker, https://github.com/feagi/feagi/issues
Classifier: Programming Language :: Python :: 3 :: Only
Classifier: License :: OSI Approved :: Apache Software License
Classifier: Operating System :: OS Independent
Requires-Python: >=3.6
License-File: LICENSE
Requires-Dist: requests
Requires-Dist: numpy
Requires-Dist: zmq
Requires-Dist: lz4
Requires-Dist: opencv-python ==4.6.0.66 ; python_version < "3.8"
